dash_shadcn/__init__.py
dash_shadcn/main.py
dash_shadcn-0.0.0.dist-info/LICENSE
dash_shadcn-0.0.0.dist-info/METADATA
dash_shadcn-0.0.0.dist-info/WHEEL
dash_shadcn-0.0.0.dist-info/RECORD
